genwiki/__init__.py
genwiki/addressbook.py
genwiki/convert.py
genwiki/djvu_catalog.py
genwiki/djvu_cmd.py
genwiki/djvu_core.py
genwiki/djvu_manager.py
genwiki/djvu_processor.py
genwiki/djvu_viewer.py
genwiki/download.py
genwiki/genwiki_cmd.py
genwiki/genwiki_paths.py
genwiki/gov_api.py
genwiki/image_convert.py
genwiki/locator.py
genwiki/multilang_querymanager.py
genwiki/nominatim.py
genwiki/params_view.py
genwiki/parquet.py
genwiki/playground.py
genwiki/query_view.py
genwiki/tarball.py
genwiki/template.py
genwiki/version.py
genwiki/webserver.py
genwiki/wiki.py
genwiki/wikidata.py
genwiki/wikidata_view.py
genwiki_examples/addressbook.puml
genwiki_examples/djvu_data.db
genwiki_examples/djvu_queries.yaml
genwiki_examples/endpoint.yaml
genwiki_examples/location.puml
genwiki_examples/queries.yaml
genwiki_examples/region_lookup.json
genwiki_examples/weimarTH1851.parquet
genwiki_examples/weimarTH1853.parquet
genwiki2024-0.0.4.dist-info/METADATA
genwiki2024-0.0.4.dist-info/WHEEL
genwiki2024-0.0.4.dist-info/entry_points.txt
genwiki2024-0.0.4.dist-info/licenses/LICENSE
genwiki2024-0.0.4.dist-info/RECORD
