Metadata-Version: 2.4
Name: genwiki2024
Version: 0.0.4
Summary: nicesprinkler
Project-URL: Home, https://github.com/WolfgangFahl/genwiki2024
Project-URL: Documentation, https://wiki.bitplan.com/index.php/genwiki2024
Project-URL: Source, https://github.com/WolfgangFahl/genwiki2024
Author-email: Wolfgang Fahl <wf@bitplan.com>
Maintainer-email: Wolfgang Fahl <wf@bitplan.com>
License-Expression: Apache-2.0
License-File: LICENSE
Keywords: genealogy,mediawiki,nicegui,semantic
Classifier: Development Status :: 4 - Beta
Classifier: Environment :: Web Environment
Classifier: Intended Audience :: Developers
Classifier: Intended Audience :: Education
Classifier: Intended Audience :: Science/Research
Classifier: License :: OSI Approved :: Apache Software License
Classifier: Operating System :: OS Independent
Classifier: Programming Language :: Python :: 3 :: Only
Classifier: Programming Language :: Python :: 3.9
Classifier: Programming Language :: Python :: 3.10
Classifier: Programming Language :: Python :: 3.11
Classifier: Programming Language :: Python :: 3.12
Classifier: Topic :: Software Development :: Libraries :: Python Modules
Requires-Python: >=3.9
Requires-Dist: djvulibre-python>=0.9.1
Requires-Dist: geocoder>=1.38.1
Requires-Dist: geopy>=2.3.0
Requires-Dist: mwparserfromhell>=0.6.6
Requires-Dist: ngwidgets>=0.22.2
Requires-Dist: nicegui>=2.1.0
Requires-Dist: numpy>=2.2.3
Requires-Dist: pillow>=11.1.0
Requires-Dist: py-3rdparty-mediawiki>=0.14.7
Requires-Dist: py-ez-wikidata>=0.2.3
Requires-Dist: pyarrow>=17.0.0
Requires-Dist: pycairo>=1.27.0
Requires-Dist: pylodstorage>=0.14.3
Requires-Dist: requests>=2.31.0
Requires-Dist: tqdm>=4.66.5
Requires-Dist: wdgrid>=0.1.2
Provides-Extra: test
Requires-Dist: green; extra == 'test'
